setup.py
BtcTurkApi.egg-info/PKG-INFO
BtcTurkApi.egg-info/SOURCES.txt
BtcTurkApi.egg-info/dependency_links.txt
BtcTurkApi.egg-info/requires.txt
BtcTurkApi.egg-info/top_level.txt
btcturkapi/__init__.py
btcturkapi/btcturkapi.py