Metadata-Version: 1.1
Name: BtcTurkApi
Version: 0.0.4
Summary: Python btcturk.com API wrapper.
Home-page: https://github.com/uguraltinsoy/BTC-TURK-API
Author: Uğur Altınsoy
Author-email: ugur.altnsy@gmail.com
License: UNKNOWN
Keywords: btcturk,btcturkapi,bitcoin,api,exchange,btc,eth,xrp
Platform: UNKNOWN
Classifier: Intended Audience :: Developers
Classifier: License :: OSI Approved :: MIT License
Classifier: Operating System :: OS Independent
Classifier: Programming Language :: Python :: 2
Classifier: Programming Language :: Python :: 2.7
Classifier: Programming Language :: Python :: 3
Classifier: Programming Language :: Python :: 3.3
Classifier: Programming Language :: Python :: 3.4
Classifier: Programming Language :: Python :: 3.5
Classifier: Programming Language :: Python :: 3.6
Classifier: Programming Language :: Python
Classifier: Topic :: Office/Business :: Financial
